jsonffi/__init__.py
jsonffi-1.0.6.dist-info/METADATA
jsonffi-1.0.6.dist-info/WHEEL
jsonffi-1.0.6.dist-info/top_level.txt
jsonffi-1.0.6.dist-info/RECORD
