Metadata-Version: 2.1
Name: jsonffi
Version: 1.0.6
Summary: 一言で書けるパッケージ概要
Home-page: https://github.com/javacommons/py-jsonffi
Author: JavaCommons Technologies
Author-email: javacommmons@gmail.com
License: MIT
Classifier: Programming Language :: Python
Classifier: Programming Language :: Python :: 3
Classifier: Programming Language :: Python :: 3.4
Classifier: Programming Language :: Python :: 3.5
Classifier: Programming Language :: Python :: 3.6
Requires-Dist: cffi
